{
    "version": "3.8.1",
    "flags": {},
    "shapes": [
        {
            "label": "window",
            "line_color": null,
            "fill_color": null,
            "points": [
                [
                    482,
                    223
                ],
                [
                    485,
                    290
                ],
                [
                    572,
                    288
                ],
                [
                    568,
                    219
                ]
            ],
            "shape_type": "polygon"
        },
        {
            "label": "window",
            "line_color": null,
            "fill_color": null,
            "points": [
                [
                    365,
                    225
                ],
                [
                    363,
                    293
                ],
                [
                    442,
                    294
                ],
                [
                    445,
                    224
                ]
            ],
            "shape_type": "polygon"
        },
        {
            "label": "window",
            "line_color": null,
            "fill_color": null,
            "points": [
                [
                    260,
                    233
                ],
                [
                    259,
                    294
                ],
                [
                    323,
                    295
                ],
                [
                    327,
                    230
                ]
            ],
            "shape_type": "polygon"
        },
        {
            "label": "window",
            "line_color": null,
            "fill_color": null,
            "points": [
                [
                    169,
                    235
                ],
                [
                    165,
                    297
                ],
                [
                    225,
                    298
                ],
                [
                    227,
                    233
                ]
            ],
            "shape_type": "polygon"
        },
        {
            "label": "window",
            "line_color": null,
            "fill_color": null,
            "points": [
                [
                    113,
                    249
                ],
                [
                    110,
                    284
                ],
                [
                    139,
                    286
                ],
                [
                    142,
                    248
                ]
            ],
            "shape_type": "polygon"
        },
        {
            "label": "window",
            "line_color": null,
            "fill_color": null,
            "points": [
                [
                    26,
                    253
                ],
                [
                    24,
                    286
                ],
                [
                    50,
                    287
                ],
                [
                    51,
                    253
                ]
            ],
            "shape_type": "polygon"
        },
        {
            "label": "window",
            "line_color": null,
            "fill_color": null,
            "points": [
                [
                    47,
                    315
                ],
                [
                    44,
                    370
                ],
                [
                    95,
                    371
                ],
                [
                    96,
                    316
                ]
            ],
            "shape_type": "polygon"
        }
    ],
    "lineColor": [
        0,
        255,
        0,
        128
    ],
    "fillColor": [
        255,
        0,
        0,
        128
    ],
    "imagePath": "01460.png",
    "imageData": null,
    "imageHeight": 480,
    "imageWidth": 640
}