{
    "version": "3.10.1",
    "flags": {},
    "shapes": [
        {
            "label": "window",
            "line_color": null,
            "fill_color": null,
            "points": [
                [
                    98,
                    69
                ],
                [
                    97,
                    133
                ],
                [
                    133,
                    133
                ],
                [
                    134,
                    68
                ]
            ],
            "shape_type": "polygon"
        },
        {
            "label": "window",
            "line_color": null,
            "fill_color": null,
            "points": [
                [
                    103,
                    185
                ],
                [
                    101,
                    251
                ],
                [
                    144,
                    251
                ],
                [
                    146,
                    186
                ]
            ],
            "shape_type": "polygon"
        },
        {
            "label": "window",
            "line_color": null,
            "fill_color": null,
            "points": [
                [
                    96,
                    309
                ],
                [
                    94,
                    402
                ],
                [
                    137,
                    400
                ],
                [
                    141,
                    311
                ]
            ],
            "shape_type": "polygon"
        },
        {
            "label": "window",
            "line_color": null,
            "fill_color": null,
            "points": [
                [
                    93,
                    454
                ],
                [
                    91,
                    544
                ],
                [
                    142,
                    542
                ],
                [
                    142,
                    452
                ]
            ],
            "shape_type": "polygon"
        },
        {
            "label": "window",
            "line_color": null,
            "fill_color": null,
            "points": [
                [
                    93,
                    590
                ],
                [
                    93,
                    687
                ],
                [
                    140,
                    687
                ],
                [
                    140,
                    588
                ]
            ],
            "shape_type": "polygon"
        },
        {
            "label": "window",
            "line_color": null,
            "fill_color": null,
            "points": [
                [
                    220,
                    67
                ],
                [
                    219,
                    131
                ],
                [
                    255,
                    131
                ],
                [
                    256,
                    66
                ]
            ],
            "shape_type": "polygon"
        },
        {
            "label": "window",
            "line_color": null,
            "fill_color": null,
            "points": [
                [
                    369,
                    67
                ],
                [
                    368,
                    131
                ],
                [
                    404,
                    131
                ],
                [
                    405,
                    66
                ]
            ],
            "shape_type": "polygon"
        },
        {
            "label": "window",
            "line_color": null,
            "fill_color": null,
            "points": [
                [
                    496,
                    70
                ],
                [
                    495,
                    134
                ],
                [
                    531,
                    134
                ],
                [
                    532,
                    69
                ]
            ],
            "shape_type": "polygon"
        },
        {
            "label": "window",
            "line_color": null,
            "fill_color": null,
            "points": [
                [
                    197,
                    184
                ],
                [
                    195,
                    250
                ],
                [
                    238,
                    250
                ],
                [
                    240,
                    185
                ]
            ],
            "shape_type": "polygon"
        },
        {
            "label": "window",
            "line_color": null,
            "fill_color": null,
            "points": [
                [
                    290,
                    183
                ],
                [
                    288,
                    249
                ],
                [
                    331,
                    249
                ],
                [
                    333,
                    184
                ]
            ],
            "shape_type": "polygon"
        },
        {
            "label": "window",
            "line_color": null,
            "fill_color": null,
            "points": [
                [
                    385,
                    184
                ],
                [
                    383,
                    250
                ],
                [
                    426,
                    250
                ],
                [
                    428,
                    185
                ]
            ],
            "shape_type": "polygon"
        },
        {
            "label": "window",
            "line_color": null,
            "fill_color": null,
            "points": [
                [
                    480,
                    185
                ],
                [
                    478,
                    251
                ],
                [
                    521,
                    251
                ],
                [
                    523,
                    186
                ]
            ],
            "shape_type": "polygon"
        },
        {
            "label": "window",
            "line_color": null,
            "fill_color": null,
            "points": [
                [
                    192,
                    307
                ],
                [
                    190,
                    400
                ],
                [
                    235,
                    399
                ],
                [
                    237,
                    309
                ]
            ],
            "shape_type": "polygon"
        },
        {
            "label": "window",
            "line_color": null,
            "fill_color": null,
            "points": [
                [
                    288,
                    305
                ],
                [
                    286,
                    398
                ],
                [
                    331,
                    397
                ],
                [
                    333,
                    307
                ]
            ],
            "shape_type": "polygon"
        },
        {
            "label": "window",
            "line_color": null,
            "fill_color": null,
            "points": [
                [
                    385,
                    306
                ],
                [
                    383,
                    399
                ],
                [
                    428,
                    398
                ],
                [
                    430,
                    308
                ]
            ],
            "shape_type": "polygon"
        },
        {
            "label": "window",
            "line_color": null,
            "fill_color": null,
            "points": [
                [
                    481,
                    307
                ],
                [
                    479,
                    400
                ],
                [
                    524,
                    399
                ],
                [
                    526,
                    309
                ]
            ],
            "shape_type": "polygon"
        },
        {
            "label": "window",
            "line_color": null,
            "fill_color": null,
            "points": [
                [
                    187,
                    452
                ],
                [
                    185,
                    542
                ],
                [
                    236,
                    540
                ],
                [
                    236,
                    450
                ]
            ],
            "shape_type": "polygon"
        },
        {
            "label": "window",
            "line_color": null,
            "fill_color": null,
            "points": [
                [
                    285,
                    452
                ],
                [
                    283,
                    542
                ],
                [
                    334,
                    540
                ],
                [
                    334,
                    450
                ]
            ],
            "shape_type": "polygon"
        },
        {
            "label": "window",
            "line_color": null,
            "fill_color": null,
            "points": [
                [
                    384,
                    450
                ],
                [
                    382,
                    545
                ],
                [
                    433,
                    543
                ],
                [
                    435,
                    450
                ]
            ],
            "shape_type": "polygon"
        },
        {
            "label": "window",
            "line_color": null,
            "fill_color": null,
            "points": [
                [
                    479,
                    452
                ],
                [
                    477,
                    547
                ],
                [
                    528,
                    545
                ],
                [
                    530,
                    452
                ]
            ],
            "shape_type": "polygon"
        },
        {
            "label": "window",
            "line_color": null,
            "fill_color": null,
            "points": [
                [
                    479,
                    452
                ],
                [
                    477,
                    547
                ],
                [
                    528,
                    545
                ],
                [
                    530,
                    452
                ]
            ],
            "shape_type": "polygon"
        },
        {
            "label": "window",
            "line_color": null,
            "fill_color": null,
            "points": [
                [
                    189,
                    589
                ],
                [
                    189,
                    686
                ],
                [
                    236,
                    686
                ],
                [
                    236,
                    587
                ]
            ],
            "shape_type": "polygon"
        },
        {
            "label": "window",
            "line_color": null,
            "fill_color": null,
            "points": [
                [
                    286,
                    590
                ],
                [
                    286,
                    687
                ],
                [
                    333,
                    687
                ],
                [
                    333,
                    588
                ]
            ],
            "shape_type": "polygon"
        },
        {
            "label": "window",
            "line_color": null,
            "fill_color": null,
            "points": [
                [
                    385,
                    590
                ],
                [
                    385,
                    687
                ],
                [
                    432,
                    687
                ],
                [
                    432,
                    588
                ]
            ],
            "shape_type": "polygon"
        },
        {
            "label": "window",
            "line_color": null,
            "fill_color": null,
            "points": [
                [
                    479,
                    590
                ],
                [
                    479,
                    687
                ],
                [
                    526,
                    687
                ],
                [
                    526,
                    588
                ]
            ],
            "shape_type": "polygon"
        },
        {
            "label": "window",
            "line_color": null,
            "fill_color": null,
            "points": [
                [
                    94,
                    733
                ],
                [
                    94,
                    830
                ],
                [
                    141,
                    830
                ],
                [
                    141,
                    731
                ]
            ],
            "shape_type": "polygon"
        },
        {
            "label": "window",
            "line_color": null,
            "fill_color": null,
            "points": [
                [
                    191,
                    734
                ],
                [
                    191,
                    831
                ],
                [
                    238,
                    831
                ],
                [
                    238,
                    732
                ]
            ],
            "shape_type": "polygon"
        },
        {
            "label": "window",
            "line_color": null,
            "fill_color": null,
            "points": [
                [
                    287,
                    736
                ],
                [
                    287,
                    833
                ],
                [
                    334,
                    833
                ],
                [
                    334,
                    734
                ]
            ],
            "shape_type": "polygon"
        },
        {
            "label": "window",
            "line_color": null,
            "fill_color": null,
            "points": [
                [
                    385,
                    734
                ],
                [
                    383,
                    813
                ],
                [
                    430,
                    812
                ],
                [
                    432,
                    732
                ]
            ],
            "shape_type": "polygon"
        },
        {
            "label": "window",
            "line_color": null,
            "fill_color": null,
            "points": [
                [
                    482,
                    735
                ],
                [
                    480,
                    814
                ],
                [
                    527,
                    813
                ],
                [
                    529,
                    733
                ]
            ],
            "shape_type": "polygon"
        }
    ],
    "lineColor": [
        0,
        255,
        0,
        128
    ],
    "fillColor": [
        255,
        0,
        0,
        128
    ],
    "imagePath": "02430.png",
    "imageData": null,
    "imageHeight": 1024,
    "imageWidth": 584
}